Metadata-Version: 2.1
Name: mbonig.cicd-spa-website
Version: 0.1.2
Summary: A CDK construct which creates a pipeline that pulls code from a source repository, builds it, then deploys to an S3 bucket (with CloudFront if a certificate is required)
Home-page: https://github.com/mbonig/cicd-spa-website
Author: Matthew Bonig<matthew.bonig@gmail.com>
License: MIT
Project-URL: Source, https://github.com/mbonig/cicd-spa-website
Platform: UNKNOWN
Classifier: Intended Audience :: Developers
Classifier: Operating System :: OS Independent
Classifier: Programming Language :: JavaScript
Classifier: Programming Language :: Python :: 3 :: Only
Classifier: Programming Language :: Python :: 3.6
Classifier: Programming Language :: Python :: 3.7
Classifier: Programming Language :: Python :: 3.8
Classifier: Typing :: Typed
Classifier: License :: OSI Approved
Requires-Python: >=3.6
